Assignment2/Q-4/Fulladder-VG1.v
//gate model


//Gate modelling of Half Adder

module halfadder(a,b,s,c);
	input a,b;
	output s,c;
	
	xor(s,a,b);
	and(c,a,b);
	
endmodule

module fulladder(x,y,z,s,c);
	input x,y,z;
	output s,c;
	wire s1,c1,c2;
	
	halfadder HA1(.a(x),.b(y),.s(s1),.c(c1));
	halfadder HA2(.a(s1),.b(z),.s(s),.c(c2));
	or (c,c1,c2);
endmodule

Assignment2/Q-4/Fulladder-V1.v
// testbench for fulladder

`timescale 1ns/1ps
module inp;
      reg x,y,z;
      wire s,c;
      fulladder M1(.x(x),.y(y),.z(z),.s(s),.c(c));
      
      initial
      begin
             $dumpfile("Fulladder-V1.vcd");
             $dumpvars(0,inp);
             
             x=1'b0;
             y=1'b0;
             z=1'b0;
             $monitor("sum = %b carry = %b",s,c);
             #1;

             x=1'b0;
             y=1'b0;
             z=1'b1;
             $monitor("sum = %b carry = %b",s,c);
             #1;

             x=1'b0;
             y=1'b1;
             z=1'b0;
             $monitor("sum = %b carry = %b",s,c);
             #1;

             x=1'b0;
             y=1'b1;
             z=1'b1;
             $monitor("sum = %b carry = %b",s,c);
             #1;

             x=1'b1;
             y=1'b0;
             z=1'b0;
             $monitor("sum = %b carry = %b",s,c);
             #1;

             x=1'b1;
             y=1'b0;
             z=1'b1;
             $monitor("sum = %b carry = %b",s,c);
             #1;

             x=1'b1;
             y=1'b1;
             z=1'b0;
             $monitor("sum = %b carry = %b",s,c);
             #1;

             x=1'b1;
             y=1'b1;
             z=1'b1;
             $monitor("sum = %b carry = %b",s,c);
 
      end
      initial #8 $finish;
endmodule

Assignment2/Q-4/Fulladder-V1.vcd
$date
	Tue Oct 17 21:04:02 2017
$end
$version
	Icarus Verilog
$end
$timescale
	1ps
$end
$scope module inp $end
$var wire 1 ! c $end
$var wire 1 " s $end
$var reg 1 # x $end
$var reg 1 $ y $end
$var reg 1 % z $end
$scope module M1 $end
$var wire 1 ! c $end
$var wire 1 & c1 $end
$var wire 1 ' c2 $end
$var wire 1 " s $end
$var wire 1 ( s1 $end
$var wire 1 ) x $end
$var wire 1 * y $end
$var wire 1 + z $end
$scope module HA1 $end
$var wire 1 ) a $end
$var wire 1 * b $end
$var wire 1 & c $end
$var wire 1 ( s $end
$upscope $end
$scope module HA2 $end
$var wire 1 ( a $end
$var wire 1 + b $end
$var wire 1 ' c $end
$var wire 1 " s $end
$upscope $end
$upscope $end
$upscope $end
$enddefinitions $end
#0
$dumpvars
0+
0*
0)
0(
0'
0&
0%
0$
0#
0"
0!
$end
#1000
1"
1%
1+
#2000
1(
0%
0+
1$
1*
#3000
1!
0"
1'
1%
1+
#4000
0!
1"
0'
0%
0+
0$
0*
1#
1)
#5000
1!
0"
1'
1%
1+
#6000
0'
0(
1&
0%
0+
1$
1*
#7000
1"
1%
1+
