Assignment2/Q-6/6a/message-VB1.v
module receiveFromA(receive, message);
input receive;
input [31:0]message;
always @(receive)
begin
    if(receive == 1)begin
        $monitor("@ time %0t ns - B received message: %d from A.", $time, message);
        end
end
endmodule    

module receiveFromB(receive, message);
input receive;
input [31:0]message;

always @(receive)
begin
    if(receive == 1)begin
         $monitor("@ time %0t ns - A received message: %d from B.", $time, message);
        end
end

endmodule    


module MachineA(send, message);
input send;
input [31:0]message;
    receiveFromA m(send, message);
endmodule

module MachineB(send, message);
input send;
input [31:0]message;
    receiveFromB m(send, message);
endmodule

Assignment2/Q-6/6a/message-V1.v
module message_tb;
reg [31:0]aMessage, bMessage;
reg aSend, bSend;


MachineA a(aSend, aMessage);
MachineB b(bSend, bMessage);

initial
begin
    $dumpfile("message-V1.vcd");
    $dumpvars(0, message_tb);
end    
    

    initial
    begin
    aSend = 0; 
    bSend = 0; 
    aMessage = 0;
    bMessage = 0;
    #10
    aSend = 1; 
    bSend = 0; 
    aMessage = 54;
    #10
    aSend = 0; 
    bSend = 1; 
    bMessage = 72;
    #10
    aSend = 1; 
    bSend = 0; 
    aMessage = 19;
    #10
    aSend = 0; 
    bSend = 1; 
    bMessage = 93;
    #10
    aSend = 1; 
    bSend = 0; 
    aMessage = 34;
    #10
    aSend = 0; 
    bSend = 1; 
    bMessage = 79;
    #10
    aSend = 1; 
    bSend = 0; 
    aMessage = 28;
    #10
    aSend = 0; 
    bSend = 1; 
    bMessage = 86;
    #10
    $finish;
    end


endmodule

Assignment2/Q-6/6a/message-V1.vcd
$date
	Tue Oct 17 22:38:58 2017
$end
$version
	Icarus Verilog
$end
$timescale
	1s
$end
$scope module message_tb $end
$var reg 32 ! aMessage [31:0] $end
$var reg 1 " aSend $end
$var reg 32 # bMessage [31:0] $end
$var reg 1 $ bSend $end
$scope module a $end
$var wire 32 % message [31:0] $end
$var wire 1 & send $end
$scope module m $end
$var wire 32 ' message [31:0] $end
$var wire 1 & receive $end
$upscope $end
$upscope $end
$scope module b $end
$var wire 32 ( message [31:0] $end
$var wire 1 ) send $end
$scope module m $end
$var wire 32 * message [31:0] $end
$var wire 1 ) receive $end
$upscope $end
$upscope $end
$upscope $end
$enddefinitions $end
#0
$dumpvars
b0 *
0)
b0 (
b0 '
0&
b0 %
0$
b0 #
0"
b0 !
$end
#10
b110110 !
b110110 %
b110110 '
1"
1&
#20
b1001000 #
b1001000 (
b1001000 *
1$
1)
0"
0&
#30
b10011 !
b10011 %
b10011 '
0$
0)
1"
1&
#40
b1011101 #
b1011101 (
b1011101 *
1$
1)
0"
0&
#50
b100010 !
b100010 %
b100010 '
0$
0)
1"
1&
#60
b1001111 #
b1001111 (
b1001111 *
1$
1)
0"
0&
#70
b11100 !
b11100 %
b11100 '
0$
0)
1"
1&
#80
b1010110 #
b1010110 (
b1010110 *
1$
1)
0"
0&
