Assignment2/Q-7/Dflipflop-VB1.v
module srlatch(r,s,q,q1);
     input r,s;
     output q,q1;
     reg q,q1;
     initial
       begin
             q=1'b0;
             q1=1'b1;
       end
       always@(s,r)
        begin
             case({s,r})
                 {1'b0,1'b0}: begin q=q; q1=q1; end
                 {1'b0,1'b1}: begin q=1'b0; q1=1'b1; end
                 {1'b1,1'b0}: begin q=1'b1; q1=1'b0; end
                 {1'b1,1'b1}: begin q=1'bx; q1=1'bx; end
             endcase
        end
endmodule

module dlatch(d,clk,q,q1);
     input d,clk;
     output q,q1;
     reg r, s;
     always @(clk, d)
     begin
       r = ~d & clk;
       s = d & clk;
       
     end
     srlatch M(r, s, q, q1);
endmodule

module dflipflop(d, clk, q, q1);
    input d, clk;
    output q, q1;
    wire qm, qm1;
    dlatch M1(d, ~clk, qm, qm1);
    dlatch M2(qm, clk, q, q1);
endmodule

Assignment2/Q-7/Dflipflop-V1.v
// testbench for dflipflop

module inp;
     reg d,clk;
     wire q,q1;
     dflipflop M3(.d(d), .clk(clk), .q(q), .q1(q1));
     initial
     begin
             $dumpfile("7-V1.vcd");
             $dumpvars(0,inp);
             $monitor("@time = %0t, clock = %d ns, d = %b ,q = %b ,q1 = %b\n",$time,clk,d,q,q1);
             
    clk = 0;
    d = 0;
end    
    

    always
    begin 
        #10 
        clk = ~clk;
    end

    initial
    begin
    #15   
    d = 1'b1;
    #30
    d = 1'b0;
    #20   
    d = 1'b0;
    #10
    d = 1'b1;
    #30   
    d = 1'b1;
    #20
    d = 1'b1;
    #15  
    d = 1'b0;
    #20
    d = 1'b1;
 
    $finish;
    end


endmodule

Assignment2/Q-7/Dflipflop-V1.vcd
$date
	Tue Oct 17 14:08:29 2017
$end
$version
	Icarus Verilog
$end
$timescale
	1s
$end
$scope module inp $end
$var wire 1 ! q $end
$var wire 1 " q1 $end
$var reg 1 # clk $end
$var reg 1 $ d $end
$scope module M3 $end
$var wire 1 % clk $end
$var wire 1 & d $end
$var wire 1 ! q $end
$var wire 1 " q1 $end
$var wire 1 ' qm $end
$var wire 1 ( qm1 $end
$scope module M1 $end
$var wire 1 ) clk $end
$var wire 1 & d $end
$var wire 1 ' q $end
$var wire 1 ( q1 $end
$var reg 1 * r $end
$var reg 1 + s $end
$scope module M $end
$var wire 1 , r $end
$var wire 1 - s $end
$var reg 1 . q $end
$var reg 1 / q1 $end
$upscope $end
$upscope $end
$scope module M2 $end
$var wire 1 % clk $end
$var wire 1 ' d $end
$var wire 1 ! q $end
$var wire 1 " q1 $end
$var reg 1 0 r $end
$var reg 1 1 s $end
$scope module M $end
$var wire 1 2 r $end
$var wire 1 3 s $end
$var reg 1 4 q $end
$var reg 1 5 q1 $end
$upscope $end
$upscope $end
$upscope $end
$upscope $end
$enddefinitions $end
#0
$dumpvars
15
04
03
02
01
00
1/
0.
0-
1,
0+
1*
1)
1(
0'
0&
0%
0$
0#
1"
0!
$end
#10
0*
0,
0)
10
12
1#
1%
#15
1$
1&
#20
0/
0(
1.
1'
1+
1-
1)
00
02
0#
0%
#30
0+
0-
05
0"
14
1!
0)
11
13
1#
1%
#40
1+
1-
1)
01
03
0#
0%
#45
1/
1(
0.
0'
0+
0-
1*
1,
0$
0&
#50
0*
0,
15
1"
04
0!
0)
10
12
1#
1%
#60
1*
1,
1)
00
02
0#
0%
#70
0*
0,
0)
10
12
1#
1%
#75
1$
1&
#80
0/
0(
1.
1'
1+
1-
1)
00
02
0#
0%
#90
0+
0-
05
0"
14
1!
0)
11
13
1#
1%
#100
1+
1-
1)
01
03
0#
0%
#110
0+
0-
0)
11
13
1#
1%
#120
1+
1-
1)
01
03
0#
0%
#130
0+
0-
0)
11
13
1#
1%
#140
1/
1(
0.
0'
1*
1,
1)
01
03
0#
0%
0$
0&
#150
0*
0,
15
1"
04
0!
0)
10
12
1#
1%
#160
0/
0(
1.
1'
1+
1-
1)
00
02
0#
0%
1$
1&
